wowool/apps/chunks/__init__.py
wowool/apps/chunks/config.py
wowool/chunks/app_id.py
wowool/chunks/chunks.py
wowool_chunks-1.3.3.dist-info/METADATA
wowool_chunks-1.3.3.dist-info/WHEEL
wowool_chunks-1.3.3.dist-info/top_level.txt
wowool_chunks-1.3.3.dist-info/RECORD
